{"config_version": "multi_ocr_v1_2026_04_11", "pdf_sha1": "f6347cf14a7f370f0a2e14955340853353d01e06", "result": {"text": "INVOICE\nFOB MIAMI\nCALA MARINE CORPORATION\nShip Via TROPICAL\n13571 SW 135 Ave. Suite 201\nMiami, FL 33186 Date Invoice #\nT: 305-254-0214 F: 305-254-0344\nFED Tax ID: 27-1299011 info@cala-marine.com 2/3/2026 26610\nBill To Ship To\nBudget Marine Grenada Tropical Shipping Grenada\nTrue Blue Bay 9505 NW 108Th Avenue\nSt. George's, Grenada Medley, FL 33178\nWest Indies Phone: (305) 805-7400\nAttn: Nicholas George\nTRADING CURRENCY - USD - $\nTerms Cust. P.O. Sales Order Prepared By\nBank Wire: AMERANT BANK\nAddress: 13571 SW 135 AVE STE 201 MIAMI FL, 33186\nABA: 067010509 Swift: MNBMUS33 Net 30 GD/07106 16697 ORS/AJ\nCala Marine Corporation Acct # 8201751006\nLine Item Description Order Inv. B/O Rate Amount\n1 DAI-DWB40-B/F702M- D-WAVE DWB SALT WATER SPIN COMBO PMB. 20 20 0 35.47 709.40\nDAIWA.\n2 DAI-FTS1102MFS- ROD-FT SURF ROD, Sections= 2, Line Wt.= 10-25 4 4 0 18.81 75.24\n3 DAI-BG8000- BG SPINNING REEL, 6 + 1, 5.3 : 1. / 850 gr. / 1 1 0 136.83 136.83\nCHINA / DAIWA.\n4 DAI-JB4U20-300IB- JB4U20-300IB, Filler Spool, Island Blue, Mono 6 6 0 13.32 79.92\nDia.= 6lb.\nTRADING CURRENCY USD - Please pay the Warranties: Any and all product warranties must be Total - USD $1,001.39\namount due within your credit terms in order to processed with manufacturer and according to\navoid a service charge of 1.5% per month on manufacturer's policies and guidelines. All returns Payments/Credits $0.00\npast due balances. must be pre-approved Cala Marine.\nBalance Due $1,001.39\nThank you for your business! WWW.CALA-MARINE.COM\nBuyer agrees to be responsible for payment in full of this invoice unless Cala Marine is notified of discrepancy within 48 hours of receipt of delivery. This notification may be made by\ntelephone, or via facsimile.El comprador se compromete a ser responsable por el pago total de la factura, a menos Cala Marine es notificado de discrepancia dentro de 48\nhoras siguientes a la recepci\u00f3n de la entrega. Esta notificaci\u00f3n puede hacerse por tel\u00e9fono o por fax.", "variants": {"pdfplumber": "INVOICE\nFOB MIAMI\nCALA MARINE CORPORATION\nShip Via TROPICAL\n13571 SW 135 Ave. Suite 201\nMiami, FL 33186 Date Invoice #\nT: 305-254-0214 F: 305-254-0344\nFED Tax ID: 27-1299011 info@cala-marine.com 2/3/2026 26610\nBill To Ship To\nBudget Marine Grenada Tropical Shipping Grenada\nTrue Blue Bay 9505 NW 108Th Avenue\nSt. George's, Grenada Medley, FL 33178\nWest Indies Phone: (305) 805-7400\nAttn: Nicholas George\nTRADING CURRENCY - USD - $\nTerms Cust. P.O. Sales Order Prepared By\nBank Wire: AMERANT BANK\nAddress: 13571 SW 135 AVE STE 201 MIAMI FL, 33186\nABA: 067010509 Swift: MNBMUS33 Net 30 GD/07106 16697 ORS/AJ\nCala Marine Corporation Acct # 8201751006\nLine Item Description Order Inv. B/O Rate Amount\n1 DAI-DWB40-B/F702M- D-WAVE DWB SALT WATER SPIN COMBO PMB. 20 20 0 35.47 709.40\nDAIWA.\n2 DAI-FTS1102MFS- ROD-FT SURF ROD, Sections= 2, Line Wt.= 10-25 4 4 0 18.81 75.24\n3 DAI-BG8000- BG SPINNING REEL, 6 + 1, 5.3 : 1. / 850 gr. / 1 1 0 136.83 136.83\nCHINA / DAIWA.\n4 DAI-JB4U20-300IB- JB4U20-300IB, Filler Spool, Island Blue, Mono 6 6 0 13.32 79.92\nDia.= 6lb.\nTRADING CURRENCY USD - Please pay the Warranties: Any and all product warranties must be Total - USD $1,001.39\namount due within your credit terms in order to processed with manufacturer and according to\navoid a service charge of 1.5% per month on manufacturer's policies and guidelines. All returns Payments/Credits $0.00\npast due balances. must be pre-approved Cala Marine.\nBalance Due $1,001.39\nThank you for your business! WWW.CALA-MARINE.COM\nBuyer agrees to be responsible for payment in full of this invoice unless Cala Marine is notified of discrepancy within 48 hours of receipt of delivery. This notification may be made by\ntelephone, or via facsimile.El comprador se compromete a ser responsable por el pago total de la factura, a menos Cala Marine es notificado de discrepancia dentro de 48\nhoras siguientes a la recepci\u00f3n de la entrega. Esta notificaci\u00f3n puede hacerse por tel\u00e9fono o por fax."}, "token_map": {"35.47": [["pdfplumber", "1 DAI-DWB40-B/F702M- D-WAVE DWB SALT WATER SPIN COMBO PMB. 20 20 0 35.47 709.40"]], "709.40": [["pdfplumber", "1 DAI-DWB40-B/F702M- D-WAVE DWB SALT WATER SPIN COMBO PMB. 20 20 0 35.47 709.40"]], "18.81": [["pdfplumber", "2 DAI-FTS1102MFS- ROD-FT SURF ROD, Sections= 2, Line Wt.= 10-25 4 4 0 18.81 75.24"]], "75.24": [["pdfplumber", "2 DAI-FTS1102MFS- ROD-FT SURF ROD, Sections= 2, Line Wt.= 10-25 4 4 0 18.81 75.24"]], "136.83": [["pdfplumber", "3 DAI-BG8000- BG SPINNING REEL, 6 + 1, 5.3 : 1. / 850 gr. / 1 1 0 136.83 136.83"], ["pdfplumber", "3 DAI-BG8000- BG SPINNING REEL, 6 + 1, 5.3 : 1. / 850 gr. / 1 1 0 136.83 136.83"]], "13.32": [["pdfplumber", "4 DAI-JB4U20-300IB- JB4U20-300IB, Filler Spool, Island Blue, Mono 6 6 0 13.32 79.92"]], "79.92": [["pdfplumber", "4 DAI-JB4U20-300IB- JB4U20-300IB, Filler Spool, Island Blue, Mono 6 6 0 13.32 79.92"]], "001.39": [["pdfplumber", "TRADING CURRENCY USD - Please pay the Warranties: Any and all product warranties must be Total - USD $1,001.39"], ["pdfplumber", "Balance Due $1,001.39"]], "0.00": [["pdfplumber", "avoid a service charge of 1.5% per month on manufacturer's policies and guidelines. All returns Payments/Credits $0.00"]]}, "confidence": 1.0, "method_stats": {"pdfplumber": 1960}, "page_count": 1, "engine_used": "pdfplumber"}}